rosdepth2mp4/__init__.py
rosdepth2mp4/_version.py
rosdepth2mp4/main.py
rosdepth2mp4-1.1.0.dist-info/LICENSE
rosdepth2mp4-1.1.0.dist-info/METADATA
rosdepth2mp4-1.1.0.dist-info/WHEEL
rosdepth2mp4-1.1.0.dist-info/entry_points.txt
rosdepth2mp4-1.1.0.dist-info/top_level.txt
rosdepth2mp4-1.1.0.dist-info/RECORD
