Metadata-Version: 2.1
Name: rosdepth2mp4
Version: 1.1.0
Summary: A simple tool to record ROS2 Depth topics to MP4.
Author-email: Katsuya Hyodo <rmsdh122@yahoo.co.jp>
License: MIT License
Project-URL: Homepage, https://github.com/PINTO0309/rosdepth2mp4
Classifier: Programming Language :: Python :: 3
Requires-Python: >=3.10
License-File: LICENSE
Requires-Dist: opencv-contrib-python >=4.9.0.80
